[
  {
    "cheetsheet_name": "The React Cheatsheet for 2020 (+ real-world examples)",
    "website_url": "https://www.freecodecamp.org/news/the-react-cheatsheet-for-2020/",
    "category": "react",
    "twitter_handle": "SavioMartin7"
  },
  {
    "cheetsheet_name": "The React Cheatsheet for 2020)",
    "website_url": "https://www.freecodecamp.org/news/the-react-cheatsheet-for-2020/",
    "category": "react",
    "twitter_handle": "SavioMartin7"
  },
  {
    "cheetsheet_name": "The React Cheatsheet for 2020 (+ real-world examples)",
    "website_url": "https://www.freecodecamp.org/news/the-react-cheatsheet-for-2020/",
    "category": "react",
    "twitter_handle": "SavioMartin7"
  },
  {
    "cheetsheet_name": "The React Cheatsheet for 2020 (+ real-world examples)",
    "website_url": "https://www.freecodecamp.org/news/the-react-cheatsheet-for-2020/",
    "category": "react",
    "twitter_handle": "SavioMartin7"
  },
  {
    "cheetsheet_name": "The React Cheatsheet for 2020 (+ real-world examples)",
    "website_url": "https://www.freecodecamp.org/news/the-react-cheatsheet-for-2020/",
    "category": "react",
    "twitter_handle": "SavioMartin7"
  },
  {
    "cheetsheet_name": "The React Cheatsheet for 2020 (+ real-world examples)",
    "website_url": "https://www.freecodecamp.org/news/the-react-cheatsheet-for-2020/",
    "category": "react",
    "twitter_handle": "SavioMartin7"
  },
  {
    "cheetsheet_name": "The React Cheatsheet for 2020 (+ real-world examples)",
    "website_url": "https://www.freecodecamp.org/news/the-react-cheatsheet-for-2020/",
    "category": "react",
    "twitter_handle": "SavioMartin7"
  },
  {
    "cheetsheet_name": "The React Cheatsheet for 2020 (+ real-world examples)",
    "website_url": "https://www.freecodecamp.org/news/the-react-cheatsheet-for-2020/",
    "category": "react",
    "twitter_handle": "SavioMartin7"
  },
  {
    "cheetsheet_name": "The React Cheatsheet for 2020 (+ real-world examples)",
    "website_url": "https://www.freecodecamp.org/news/the-react-cheatsheet-for-2020/",
    "category": "react",
    "twitter_handle": "SavioMartin7"
  }
]